alise/.gitignore
alise/README.md
alise/__init__.py
alise/cli.py
alise/config.py
alise/daemon.py
alise/database.py
alise/exceptions.py
alise/logsetup.py
alise/models.py
alise/oauth2_config.py
alise/parse_args.py
alise/pathdiversion.py
alise/router_api.py
alise/router_ssr.py
alise/etc/alise.conf
alise/etc/alise.service
alise/etc/nginx.alise
alise/static/ALISE-design-doc.pdf
alise/static/alise.svg
alise/static/aup.html
alise/static/egi.svg
alise/static/fake-internal.svg
alise/static/fake-stamp-vector-vector.zip
alise/static/favicon.ico
alise/static/github.svg
alise/static/google-oauth2.svg
alise/static/helmholtz.svg
alise/static/index.html
alise/static/kbfi.svg
alise/static/kit-fels.svg
alise/static/logo.png
alise/static/logo.svg
alise/static/privacy.html
alise/static/user-avatar.png
alise/static/vega-hpc.png
alise/static/vega-kc.svg
alise/templates/base.html
alise/templates/index.html
alise/templates/root.html
alise/templates/site.html
alise/templates/users.html
alise-1.1.5.dist-info/licenses/LICENSE
alise-1.1.5.dist-info/METADATA
alise-1.1.5.dist-info/WHEEL
alise-1.1.5.dist-info/entry_points.txt
alise-1.1.5.dist-info/pbr.json
alise-1.1.5.dist-info/top_level.txt
alise-1.1.5.dist-info/RECORD
