Metadata-Version: 2.4
Name: alise
Version: 1.1.5
Summary: Tool to link accounts
Home-page: https://github.com/marcvs/alise
Author: Marcus Hardt
Author-email: hardt@kit.edu
License: MIT license
Project-URL: Bug Tracker, https://github.com/marcvs/alise/issues
Project-URL: Documentation, https://alise.readthedocs.io/en/latest/
Classifier: Programming Language :: Python :: 3
License-File: LICENSE
Requires-Dist: fastapi
Requires-Dist: flaat
Requires-Dist: fastapi-oauth2
Requires-Dist: addict
Requires-Dist: uvicorn
Requires-Dist: python-dotenv
Requires-Dist: jinja2-time
Requires-Dist: python-dotenv
Requires-Dist: build
Dynamic: author
Dynamic: author-email
Dynamic: classifier
Dynamic: description
Dynamic: description-content-type
Dynamic: home-page
Dynamic: license
Dynamic: license-file
Dynamic: project-url
Dynamic: requires-dist
Dynamic: summary
